pdf_examiner/Action.py
pdf_examiner/Controller.py
pdf_examiner/FileResult.py
pdf_examiner/PatternResult.py
pdf_examiner/Type.py
pdf_examiner/__init__.py
pdf_examiner/__main__.py
pdf_examiner/data/__init__.py
pdf_examiner/data/options.json
pdf_examiner-1.0.0.dist-info/LICENSE.md
pdf_examiner-1.0.0.dist-info/METADATA
pdf_examiner-1.0.0.dist-info/WHEEL
pdf_examiner-1.0.0.dist-info/entry_points.txt
pdf_examiner-1.0.0.dist-info/top_level.txt
pdf_examiner-1.0.0.dist-info/RECORD
