Metadata-Version: 2.1
Name: pdf-examiner
Version: 1.0.0
Summary: Provides an overview of the inner file structure of a PDF and extracts /URI and /JS data.
Home-page: https://github.com/5f0ne/pdf-examiner
Author: 5f0
License: MIT
Classifier: Operating System :: OS Independent 
Classifier: Programming Language :: Python :: 3 
Classifier: License :: OSI Approved :: MIT License 
License-File: LICENSE.md
Requires-Dist: hash-calc
